dsconv/__init__.py
dsconv/dsconv.py
dsconv-0.0.1.dist-info/METADATA
dsconv-0.0.1.dist-info/WHEEL
dsconv-0.0.1.dist-info/licenses/AUTHORS.md
dsconv-0.0.1.dist-info/licenses/AUTHORS.md~
dsconv-0.0.1.dist-info/licenses/LICENSE.txt
dsconv-0.0.1.dist-info/licenses/LICENSE~
dsconv-0.0.1.dist-info/RECORD
