Metadata-Version: 2.4
Name: dsconv
Version: 0.0.1
Summary: Template project for PyPI publication of a package using GitLab CI/CD that implements multiple down-sampled convolutions.
Author-email: Pascal Carrivain <pascal.carrivain@inria.fr>
License: BSD 3-Clause License
License-File: AUTHORS.md
License-File: AUTHORS.md~
License-File: LICENSE.txt
License-File: LICENSE~
Classifier: License :: OSI Approved :: BSD License
Classifier: Operating System :: OS Independent
Classifier: Programming Language :: Python :: 3
Requires-Python: >=3.11
Requires-Dist: numba
Requires-Dist: numpy>=2.0
